import_yocto_bm/__init__.py
import_yocto_bm/config.py
import_yocto_bm/global_values.py
import_yocto_bm/main.py
import_yocto_bm/process.py
import_yocto_bm/utils.py
import_yocto_bm-2.8.dist-info/LICENSE
import_yocto_bm-2.8.dist-info/METADATA
import_yocto_bm-2.8.dist-info/WHEEL
import_yocto_bm-2.8.dist-info/entry_points.txt
import_yocto_bm-2.8.dist-info/top_level.txt
import_yocto_bm-2.8.dist-info/RECORD
