Metadata-Version: 2.1
Name: import-yocto-bm
Version: 2.8
Summary: Process a built Yocto project to create a Black Duck project version
Home-page: https://github.com/blackducksoftware/import_yocto_bm
Author: Matthew Brady
Author-email: w3matt@gmail.com
Classifier: Programming Language :: Python :: 3
Classifier: License :: OSI Approved :: Apache Software License
Classifier: Operating System :: OS Independent
Requires-Python: >=3.0
License-File: LICENSE
Requires-Dist: blackduck >=1.0.4
Requires-Dist: requests
